QSugar/__init__.py
QSugar/layout.py
QSugar/prop.py
QSugar/utils.py
QSugar/widgets.py
QSugar-0.3.0.dist-info/LICENSE
QSugar-0.3.0.dist-info/METADATA
QSugar-0.3.0.dist-info/WHEEL
QSugar-0.3.0.dist-info/top_level.txt
QSugar-0.3.0.dist-info/RECORD
