Metadata-Version: 2.1
Name: QSugar
Version: 0.3.0
Summary: PyQt/PySide framework, dedicated to more modern UI design. Based on interface injection, achieve separation of interface and data, as well as hierarchical layout design. It is recommended to use it in conjunction with the QBinder framework.
Home-page: https://github.com/AtticRat/QSugar
Author: Attic
Author-email: mornorrisjie@gmail.com
License: MIT
Classifier: Development Status :: 3 - Alpha
Classifier: Intended Audience :: Developers
Classifier: License :: OSI Approved :: MIT License
Classifier: Programming Language :: Python
Classifier: Programming Language :: Python :: 3
Classifier: Programming Language :: Python :: 3.6
Classifier: Programming Language :: Python :: 3.7
Classifier: Programming Language :: Python :: 3.8
Classifier: Programming Language :: Python :: 3.9
Classifier: Programming Language :: Python :: 3.10
License-File: LICENSE
Requires-Dist: Qt.py
Requires-Dist: QBinder
